pythonic_fp/iterables/__init__.py
pythonic_fp/iterables/__init__.pyi
pythonic_fp/iterables/drop_take.py
pythonic_fp/iterables/drop_take.pyi
pythonic_fp/iterables/folding.py
pythonic_fp/iterables/folding.pyi
pythonic_fp/iterables/merging.py
pythonic_fp/iterables/merging.pyi
pythonic_fp/iterables/py.typed
pythonic_fp_iterables-5.1.3.dist-info/licenses/LICENSE
pythonic_fp_iterables-5.1.3.dist-info/WHEEL
pythonic_fp_iterables-5.1.3.dist-info/METADATA
pythonic_fp_iterables-5.1.3.dist-info/RECORD
